rin_db_exc/PIQ.py
rin_db_exc/__init__.py
rin_db_exc/app.py
rin_db_exc/app_funcs.py
rin_db_exc/config.yaml
rin_db_exc/log_error.py
rin_db_exc/logging.yaml
rin_db_exc/main_cli.py
rin_db_exc/process_tasks.py
atk_training_rin_q_basic-0.1.0.dist-info/METADATA
atk_training_rin_q_basic-0.1.0.dist-info/WHEEL
atk_training_rin_q_basic-0.1.0.dist-info/entry_points.txt
atk_training_rin_q_basic-0.1.0.dist-info/RECORD
